omidb-0.13.1.dist-info/METADATA
omidb-0.13.1.dist-info/WHEEL
omidb-0.13.1.dist-info/entry_points.txt
omidb-0.13.1.dist-info/licenses/LICENSE
omidb/__init__.py
omidb/classificationtools.py
omidb/client.py
omidb/client_parser.py
omidb/commands/__init__.py
omidb/commands/summarise.py
omidb/episode.py
omidb/events.py
omidb/filters.py
omidb/image.py
omidb/lesion.py
omidb/mark.py
omidb/parser.py
omidb/series.py
omidb/study.py
omidb/utilities.py
omidb-0.13.1.dist-info/RECORD
