Metadata-Version: 2.1
Name: omidb
Version: 0.13.1
Summary: Python package and CLI for The OPTIMAM Mammography Image Database (OMI-DB)
Author-Email: Dominic Ward <dominic.ward1@nhs.net>
License: MIT
Requires-Python: >=3.7
Requires-Dist: click>=7.0
Requires-Dist: matplotlib>=3.1.2
Requires-Dist: loguru>=0.4.1
Requires-Dist: pydicom>=1.4.1
